{"i":{"0":{"id":"0","pid":"201676","type":"project","setup":{"customColors":["#0000ff","#ff0000","#30518c","#0087cb","#3ebfac","#ebf0fe","#ea77e7","#000000","#2b0050","#3c1053","#71c5e8","#00594c"],"projectImage":{"pos":{"crop":{"poi":{"x":1113.5,"y":540.5}}},"measures":{"size":{"width":1921,"height":1081}},"original":{"rType":"asset","rSubType":"image","fileName":"Mesa de trabajo 142.png","fileSize":122510,"val":"mc-dae55ddec241da7a8b2389486ecf32a3.png","aid":"ZrShNkKN5"}},"projectLogo":{"pos":{"crop":{"poi":{"x":549,"y":67.5}}},"measures":{"size":{"width":952,"height":137}},"original":{"rType":"asset","rSubType":"image","fileName":"PMI logo.png","fileSize":26130,"val":"mc-ce9ad6d2116b2f02597feaabcc677b5c.png","aid":"gG-FOdFOX"}},"skinColor":"#82A419","backgroundType":"image","titlesFont":{"id":"noto_serif"},"styleImage":{"pos":{"crop":{"poi":{"x":418.5,"y":210}}},"measures":{"size":{"width":670,"height":420}}},"customColorsDescriptionsById":{},"name":{"val":"Fundamentos de los principios de abastecimiento responsable","rType":"text"},"customColorsOrderedIds":["0","1","2","3","4","5","6","7","8","9","10","11"],"completionWindow":{"enabled":false,"message":{"val":"¡Enhorabuena! Has completado el curso.","rType":"text"}},"backgroundImage":{"pos":{"crop":{"poi":{"x":825.5,"y":540.5}}},"measures":{"size":{"width":2021,"height":1081}},"original":{"rType":"asset","rSubType":"image","fileName":"Mesa de trabajo 46.png","fileSize":30497,"val":"mc-fb4f16397efdc0ada84b0708e8b5c55d.png","aid":"Kc7Bm7d1B"}},"lang":"en-US","font":{"id":"nunito_rounded"},"customGradients":{"byId":{},"order":[]},"projectType":"classic","pos":["t0VxXKmug0","7J3sftuLT","sAIIgUEZL"],"cover":{"type":"none"},"themeColors":{"colorsById":{"var(--TC9)":{"id":"var(--TC9)","type":"derived","baseId":"var(--TC1)","derivation":{"H":-0.03,"L":0.16137254901960785,"S":-0.09999999999999998},"name":"Primary Variant 3","description":"For graphics"},"var(--TC8)":{"id":"var(--TC8)","type":"derived","name":"Primary Variant 2","colorByPaletteId":{"1":"#266b9b","2":"#266b9b","3":"#266b9b","4":"#266b9b","5":"#266b9b","6":"#266b9b","7":"#266b9b","8":"#266b9b","9":"#266b9b","17":"#266b9b","18":"#266b9b","20":"#266b9b","21":"#266b9b","22":"#266b9b","23":"#266b9b","24":"#266b9b","25":"#266b9b","26":"#266b9b"},"baseId":"var(--TC1)","derivation":{"S":-0.21631799163179932,"L":-0.018627450980392146,"H":-0.06},"description":"For graphics"},"var(--TC7)":{"id":"var(--TC7)","type":"derived","baseId":"var(--TC1)","derivation":{"H":-0.1,"S":-0.21631799163179932,"L":-0.06862745098039214},"name":"Primary Variant 1","description":"For graphics"},"var(--TC6)":{"id":"var(--TC6)","type":"static","colorByPaletteId":{"1":"#d51e29","2":"#d51e29","3":"#d51e29","4":"#d51e29","5":"#d51e29","6":"#d51e29","7":"#d51e29","8":"#d51e29","9":"#d51e29","17":"#d51e29","18":"#d51e29","20":"#d51e29","21":"#d51e29","22":"#d51e29","23":"#d51e29","24":"#d51e29","25":"#d51e29","26":"#d51e29"},"name":"Error","color":"#d51e29","description":"Incorrect feedback"},"var(--TC5)":{"id":"var(--TC5)","type":"static","name":"Ok","colorByPaletteId":{"1":"#729600","2":"#729600","3":"#729600","4":"#729600","5":"#729600","6":"#729600","7":"#729600","8":"#729600","9":"#729600","17":"#729600","18":"#729600","20":"#729600","21":"#729600","22":"#729600","23":"#729600","24":"#729600","25":"#729600","26":"#729600"},"color":"#729600","description":"Correct feedback"},"var(--TC4)":{"id":"var(--TC4)","type":"derived","baseId":"var(--TC2)","name":"Text Variant","derivation":{"L":0.23039215686274506},"description":" Titles/Subtitles"},"var(--TC3)":{"id":"var(--TC3)","type":"directDynamic","colorByPaletteId":{"1":"#ffffff","2":"#19014b","3":"#f3fdff","4":"#f5fff0","5":"#fcfff5","6":"#343434","7":"#dcf3fa","8":"#f4f4f4","9":"#e1e1e1","17":"#fff7f0","18":"#f0f9fa","20":"#f4f4ed","21":"#ff9635","22":"#fff6f0","23":"#1e1e1d","24":"#1b3837","25":"#1e1d1d","26":"#36020f"},"name":"Background","allowVoid":false,"description":"Slide/panels backgrounds"},"var(--TC2)":{"id":"var(--TC2)","type":"directDynamic","colorByPaletteId":{"1":"#151515","2":"#9cf4cf","3":"#050c1b","4":"#181d18","5":"#a17511","6":"#ff9090","7":"#1d2335","8":"#070707","9":"#000000","17":"#5b7777","18":"#53556f","20":"#1b2159","21":"#4e0c35","22":"#3c3026","23":"#bfbcb6","24":"#a5bdba","25":"#b9b4b2","26":"#e6d7dc"},"name":"Text","description":"Reading text"},"var(--TC1)":{"id":"var(--TC1)","type":"directDynamic","colorByPaletteId":{"1":"#e50a4f","2":"#f55bff","3":"#1577db","4":"#75ad11","5":"#593d22","6":"#ff3737","7":"#a09051","8":"#d4c616","9":"#777777","17":"#ca8181","18":"#8197ca","20":"#ef233c","21":"#b60021","22":"#995ac8","23":"#f6b414","24":"#66d7c8","25":"#ff3400","26":"#de1657"},"name":"Primary","description":"Highlight elements"},"var(--TC14)":{"id":"var(--TC14)","type":"static","color":"#ffffff","name":"White","description":"Infographic Title"},"var(--TC13)":{"id":"var(--TC13)","type":"static","name":"Black","description":"Infographic text"},"var(--TC11)":{"id":"var(--TC11)","type":"derived","name":"Primary Variant 5","baseId":"var(--TC1)","derivation":{"S":-0.11631799163179923,"L":0.08137254901960789,"H":0.1},"description":"For graphics"},"var(--TC10)":{"id":"var(--TC10)","type":"derived","baseId":"var(--TC1)","derivation":{"H":0.05,"L":0.13137254901960782,"S":-0.11631799163179923},"name":"Primary Variant 4","description":"For graphics"}},"colorsOrder":["var(--TC1)","var(--TC2)","var(--TC3)","var(--TC4)","var(--TC5)","var(--TC6)","var(--TC7)","var(--TC8)","var(--TC9)","var(--TC10)","var(--TC11)","var(--TC13)","var(--TC14)"],"palettesById":{"1":{"id":"1","name":"Basic Colors"},"2":{"id":"2","name":"Source Code"},"3":{"id":"3","name":"Cobalt Blue"},"4":{"id":"4","name":"Irish Mood"},"5":{"id":"5","name":"Roasted Pumpkin"},"6":{"id":"6","name":"Scarlet Night"},"7":{"id":"7","name":"Turquoise Islands"},"8":{"id":"8","name":"Sulphur Graphite"},"9":{"id":"9","name":"Neutral Zone"},"17":{"id":"17","name":"Spring Cottage"},"18":{"id":"18","name":"Soft Horizon"},"20":{"id":"20","name":"Ballpen Drawing"},"21":{"id":"21","name":"Ferocious Sunset"},"22":{"id":"22","name":"Blueberry Cake"},"23":{"id":"23","name":"Road Works"},"24":{"id":"24","name":"Winter Lichen"},"25":{"id":"25","name":"Danger Sign"},"26":{"id":"26","name":"Red Wine"}},"palettesOrder":["1","2","3","4","5","6","7","8","9","17","18","20","21","22","23","24","25","26"],"selectedPaletteId":"18","customPalettesById":{},"customPalettesOrder":[]},"customColorsNamesById":[{"val":"blue","rType":"colorLabel"},{"val":"red","rType":"colorLabel"}],"themeGradients":{"byId":{"vsY7U9CJP":{"stops":[{"color":"var(--TC1)","pos":0},{"color":"var(--TC2)","pos":100}]}},"order":["vsY7U9CJP"]}},"publication":{"type":"scorm12","config":{"scorm12":{"trackingMode":"eval"}}},"evaluation":{"members":{"B1E1V5qS4":{"id":"B1E1V5qS4","type":"item","size":7,"enabled":true,"cover":{"pos":{"crop":{"poi":{"x":1113.5,"y":540.5}}},"measures":{"size":{"width":1921,"height":1081}}}}},"cutOff":80,"attempts":3}},"GsAto5bCF":{"id":"GsAto5bCF","type":"slide","setup":{"templateId":"308","pos":["kUB0bGJ6T","owcOpBxa5","DOFdUOLkF","void3","void4","void5","void6","void7","void8","void9","void10","void11","void12","void13","void14","void15","void16","void17","void18","void19"]}},"BnnM3T6TJ":{"id":"BnnM3T6TJ","type":"slide","setup":{"templateId":"101","pos":["wDQMCxk_MP","void1","void2","void3","void4","void5","void6","void7","void8","void9","void10","void11","void12","void13","void14","void15","void16","void17","void18","void19"]}},"ZmY2MI1y1":{"id":"ZmY2MI1y1","type":"slide","setup":{"templateId":"343","pos":["qorEBB6iR8","AIPT2VN6-G","YYzr1QzgTb","void3","void4","void5","void6","void7","void8","void9","void10","void11","void12","void13","void14","void15","void16","void17","void18","void19"]}},"t0VxXKmug0":{"id":"t0VxXKmug0","type":"section","setup":{"pos":["0RFBUa7xZ","RbXiDZu5QA","JVPnUvQm7","tGkGJG9Qv"],"title":{"val":"Welcome to RSP Fundamentals","rType":"text"}}},"Komx8QyZm":{"id":"Komx8QyZm","type":"slide","setup":{"templateId":"209","pos":["PNG_b5VdJJ","UWQxR68JQc","void2","void3","void4","void5","void6","void7","void8","void9","void10","void11","void12","void13","void14","void15","void16","void17","void18","void19"]}},"aBovo4OtX":{"id":"aBovo4OtX","type":"subsection","setup":{"pos":["WgLLsAyzw","hDH9AaJXZ","IZ9vqh7JE","SbyMUhGkp"],"title":{"val":"Principios medioambientales ","rType":"text"}}},"Sf3TyMslO5N":{"id":"Sf3TyMslO5N","type":"slide","setup":{"templateId":"101","pos":["1pHflRZTY","void1","void2","void3","void4","void5","void6","void7","void8","void9","void10","void11","void12","void13","void14","void15","void16","void17","void18","void19"]}},"RbXiDZu5QA":{"id":"RbXiDZu5QA","type":"subsection","setup":{"pos":["Sf3TyMslO5N"],"title":{"val":" RSP Alcance e importancia para PMI (vídeo)","rType":"text"}}},"_s8kXlnmb":{"id":"_s8kXlnmb","type":"slide","setup":{"templateId":"520","pos":["XZLV08YzoF","ABsdKaNSUn","jDWRiczEoX","U-16CYlylc","7DjIXssmLJ","void5","void6","void7","void8","void9","void10","void11","void12","void13","void14","void15","void16","void17","void18","void19"]}},"IcPxssQIb":{"id":"IcPxssQIb","type":"slide","setup":{"templateId":"520","pos":["W0iXmghz1","e8ebQ_TR5","Qwri2nmAs","c090byJ--","UJz2mnYp8","void1","void0","void7","void8","void9","void10","void11","void12","void13","void14","void15","void16","void17","void18","void19"]}},"xpRBXZHNX":{"id":"xpRBXZHNX","type":"subsection","setup":{"pos":["j-4745D2ya"],"title":{"val":"Alzando la voz","rType":"text"}}},"XO7FLOlKQ":{"id":"XO7FLOlKQ","type":"slide","setup":{"templateId":"343","pos":["gBBa4wH1_","hRWDQCEvL","Bfy-p-cDI","void0","void1","void5","void6","void7","void8","void9","void10","void11","void12","void13","void14","void15","void16","void17","void18","void19"]}},"IZ9vqh7JE":{"id":"IZ9vqh7JE","type":"slide","setup":{"templateId":"509","pos":["hctu5ldMA","4bw4D6T6Q","B_Yv7XnQ7","bdPfFVIAv","ZzC4CjH8o","void5","void6","void7","void8","void9","void10","void11","void12","void13","void14","void15","void16","void17","void18","void19"]}},"MHO03WNxQ5":{"id":"MHO03WNxQ5","type":"subsection","setup":{"pos":["GsAto5bCF"],"title":{"val":"¿Qué puedes hacer como empleado de PMI? ","rType":"text"}}},"TsnJYxNdxv":{"id":"TsnJYxNdxv","type":"slide","setup":{"templateId":"101","pos":["oEwAE0shS","void1","void2","void3","void4","void5","void6","void7","void8","void9","void10","void11","void12","void13","void14","void15","void16","void17","void18","void19"]}},"CHh0iuH4t":{"id":"CHh0iuH4t","type":"slide","setup":{"templateId":"209","pos":["-DHvHm7h6v","FGkE_FSEyk","void2","void3","void4","void5","void6","void7","void8","void9","void10","void11","void12","void13","void14","void15","void16","void17","void18","void19"]}},"ZEmr3WctT":{"id":"ZEmr3WctT","type":"slide","setup":{"templateId":"344","pos":["wKsToCj6i","zfWHmrMDn","_o7xE4_M7","8WMLEA9ic","void4","void5","void6","void7","void8","void9","void10","void11","void12","void13","void14","void15","void16","void17","void18","void19"]}},"0RFBUa7xZ":{"id":"0RFBUa7xZ","type":"subsection","setup":{"pos":["TsnJYxNdxv"],"title":{"val":"Portada ","rType":"text"}}},"JVPnUvQm7":{"id":"JVPnUvQm7","type":"subsection","setup":{"pos":["XO7FLOlKQ"],"title":{"val":"Introduccion (texto)","rType":"text"}}},"E9NVCcxzn":{"id":"E9NVCcxzn","type":"subsection","setup":{"pos":["BnnM3T6TJ","hxsNDUEYf","IcPxssQIb","_s8kXlnmb","ZmY2MI1y1"],"title":{"val":"Principios de derechos humanos ","rType":"text"}}},"tGkGJG9Qv":{"id":"tGkGJG9Qv","type":"subsection","setup":{"pos":["xowoSBGcs"],"title":{"val":"RSP Estructura_ El viaje","rType":"text"}}},"T6HpKM4k7":{"id":"T6HpKM4k7","type":"slide","setup":{"templateId":"343","pos":["NKzGBebjb","21_SDzF-g","twgaoY7lk","void3","void4","void5","void6","void7","void8","void9","void10","void11","void12","void13","void14","void15","void16","void17","void18","void19"]}},"WgWur3PHXF":{"id":"WgWur3PHXF","type":"subsection","setup":{"pos":["_OiKIx4gK","ZEmr3WctT","CHh0iuH4t","Komx8QyZm","T6HpKM4k7"],"title":{"val":"Cumplimiento de la legislación y principios de integridad empresarial ","rType":"text"}}},"SbyMUhGkp":{"id":"SbyMUhGkp","type":"slide","setup":{"templateId":"343","pos":["Gfa4uq7mjE","ZQT_LMinU3","WrJ6KsAyPP","void3","void4","void5","void6","void7","void8","void9","void10","void11","void12","void13","void14","void15","void16","void17","void18","void19"]}},"hxsNDUEYf":{"id":"hxsNDUEYf","type":"slide","setup":{"templateId":"324","pos":["OqoYq6WOeX","pFs1VmP3e","7tRwxyhU2","void0","void4","void5","void6","void7","void8","void9","void10","void11","void12","void13","void14","void15","void16","void17","void18","void19"]}},"_OiKIx4gK":{"id":"_OiKIx4gK","type":"slide","setup":{"templateId":"101","pos":["YABxWeLQdq","void1","void2","void3","void4","void5","void6","void7","void8","void9","void10","void11","void12","void13","void14","void15","void16","void17","void18","void19"]}},"WgLLsAyzw":{"id":"WgLLsAyzw","type":"slide","setup":{"templateId":"101","pos":["UGwTSVJNm-","void1","void2","void3","void4","void5","void6","void7","void8","void9","void10","void11","void12","void13","void14","void15","void16","void17","void18","void19"]}},"xowoSBGcs":{"id":"xowoSBGcs","type":"slide","setup":{"templateId":"209","pos":["7mCGtqSbde","jaIIfkyNMF","void2","void3","void4","void5","void6","void7","void8","void9","void10","void11","void12","void13","void14","void15","void16","void17","void18","void19"]}},"sAIIgUEZL":{"id":"sAIIgUEZL","type":"section","setup":{"pos":["MHO03WNxQ5","xpRBXZHNX"],"title":{"val":"Alzando la voz","rType":"text"}}},"7J3sftuLT":{"id":"7J3sftuLT","type":"section","setup":{"pos":["WgWur3PHXF","E9NVCcxzn","aBovo4OtX"],"title":{"val":"Fundamental Principles","rType":"text"}}},"j-4745D2ya":{"id":"j-4745D2ya","type":"slide","setup":{"templateId":"101","pos":["luBxdGaxe","void1","void2","void3","void4","void5","void6","void7","void8","void9","void10","void11","void12","void13","void14","void15","void16","void17","void18","void19"]}},"hDH9AaJXZ":{"id":"hDH9AaJXZ","type":"slide","setup":{"templateId":"344","pos":["kq6b76hnYZ","IYOxerWbDH","P9fgWLHzag","void3","void4","void5","void6","void7","void8","void9","void10","void11","void12","void13","void14","void15","void16","void17","void18","void19"]}}},"v":"1"}