{"i":{"hDH9AaJXZ":{"id":"hDH9AaJXZ","type":"slide","setup":{"bord":{"size":0,"rad":0},"bg":{"selectedKey":"image","fill":{"opac":1,"rgb":"var(--TC3)"},"img":{"filt":{"opac":100,"gray":0,"blur":0,"tint":{"rgb":"#FFF","opac":0}},"pos":{"type":"crop","fit":{"bg":{"color":{"rgb":"#FFF","opac":100},"gradient":{"angle":0,"opac":0.5,"stops":[{"color":"#000000","pos":0},{"color":"#000000","pos":100}]}},"vali":"center","hali":"center"},"crop":{"bg":{"color":{"rgb":"#FFF","opac":0},"gradient":{"angle":0,"opac":0.5,"stops":[{"color":"#000000","pos":0},{"color":"#000000","pos":100}]}},"poi":{"x":1113.5,"y":540.5}},"mask":{"shape":1,"bg":{"color":{"rgb":"#FFF","opac":0},"gradient":{"angle":0,"opac":0.5,"stops":[{"color":"#000000","pos":0},{"color":"#000000","pos":100}]}}}},"measures":{"size":{"width":1921,"height":1081}},"orig":{"rType":"asset","rSubType":"image","fileName":"DERECHOS_HUMANOS.png","fileSize":22176,"aid":"Cxzj93jT5N","val":"mc-3fa7b39456b6d4699675f3b14f9558cf.png"}}},"transparentBg":{"selectedKey":false}}},"IYOxerWbDH":{"id":"IYOxerWbDH","type":"interactive","subtype":"interactiveRichText","setup":{"frmeTp":{"selectedKey":"noneFrame"},"bg":{"selectedKey":"fill","fill":{"opac":0,"rgb":"#FFF"}},"txt":{"val":{"ops":[{"insert":"This sub-section of the RSP outlines the mandatory Environmental requirements for Suppliers working with PMI.","attributes":{"color":"#ffffff"}},{"insert":"\n\n","attributes":{"size":"medium"}},{"insert":"If you observe issues or misalignments from environmental principles of the RSP, it is your responsibility to speak up.","attributes":{"bold":true,"italic":true,"color":"#ffffff"}},{"insert":"\n","attributes":{"size":"medium"}}]},"rType":"richtext"},"paddV1":25,"vali":"middle"}},"P9fgWLHzag":{"id":"P9fgWLHzag","type":"interactive","subtype":"interactiveImageText","setup":{"style":{"selectedKey":"overlapping"},"animation":{"selectedKey":false},"txtBg":{"fill":{"opac":0.5,"rgb":"#3ebfac"}},"bg":{"img":{"filt":{"opac":100,"gray":0,"blur":0,"tint":{"rgb":"#FFF","opac":0}},"pos":{"type":"crop","fit":{"bg":{"color":{"rgb":"#FFF","opac":100},"gradient":{"angle":0,"opac":0.5,"stops":[{"color":"#000000","pos":0},{"color":"#000000","pos":100}]}},"vali":"center","hali":"center"},"crop":{"bg":{"color":{"rgb":"#FFF","opac":0},"gradient":{"angle":0,"opac":0.5,"stops":[{"color":"#000000","pos":0},{"color":"#000000","pos":100}]}},"poi":{"x":552,"y":360}},"mask":{"shape":1,"bg":{"color":{"rgb":"#FFF","opac":0},"gradient":{"angle":0,"opac":0.5,"stops":[{"color":"#000000","pos":0},{"color":"#000000","pos":100}]}}}},"measures":{"size":{"width":1080,"height":720}},"orig":{"rType":"asset","rSubType":"image","fileName":"unsplash.jpg","fileSize":0,"val":"mc-e07597d28c42aef135bb633b649272d7.jpg","aid":"thW34_VnG"}}},"txt":{"val":{"ops":[{"insert":"\n"},{"insert":"\n","attributes":{"list":"bullet"}},{"insert":"\n","attributes":{"size":"medium"}}]},"rType":"richtext"}}},"kq6b76hnYZ":{"id":"kq6b76hnYZ","type":"interactive","subtype":"interactiveImageText","setup":{"style":{"selectedKey":"overlapping"},"animation":{"selectedKey":false},"txtBg":{"fill":{"opac":0,"rgb":"#000"}},"bg":{"img":{"filt":{"opac":100,"gray":0,"blur":0,"tint":{"rgb":"#FFF","opac":0}},"pos":{"type":"crop","fit":{"bg":{"color":{"rgb":"#ebf0fe","opac":1},"gradient":{"angle":0,"opac":0.5,"stops":[{"color":"#000000","pos":0},{"color":"#000000","pos":100}]}},"vali":"center","hali":"center"},"crop":{"bg":{"color":{"rgb":"#FFF","opac":0},"gradient":{"angle":0,"opac":0.5,"stops":[{"color":"#000000","pos":0},{"color":"#000000","pos":100}]}},"poi":{"x":997,"y":17}},"mask":{"shape":1,"bg":{"color":{"rgb":"#FFF","opac":0},"gradient":{"angle":0,"opac":0.5,"stops":[{"color":"#000000","pos":0},{"color":"#000000","pos":100}]}}}},"measures":{"size":{"width":1921,"height":1081}},"orig":{"rType":"asset","rSubType":"image","fileName":"DERECHOS_HUMANOS.png","fileSize":22176,"val":"mc-3fa7b39456b6d4699675f3b14f9558cf.png","aid":"91_009cqa6"}}},"txt":{"val":{"ops":[{"insert":"HUMAN RIGHTS","attributes":{"color":"var(--TC14)"}},{"insert":"\n","attributes":{"size":"largeTitle","align":"right"}}]},"rType":"richtext"},"hali":"","paddV1":34,"vali":"top"}}},"v":"1"}